ygt.py
hooks/hook-freetype.py
hooks/hook-uharfbuzz.py
hooks/hook-xgridfit.py
ygt/__init__.py
ygt/__main__.py
ygt/cvGuesser.py
ygt/fontViewDialog.py
ygt/freetypeFont.py
ygt/glyphPicker.py
ygt/harfbuzzFont.py
ygt/macfuncDialog.py
ygt/makeCVDialog.py
ygt/window.py
ygt/writeVTT.py
ygt/ygError.py
ygt/ygHintEditor.py
ygt/ygLabel.py
ygt/ygModel.py
ygt/ygPreferences.py
ygt/ygPreview.py
ygt/ygSchema.py
ygt/ygStems.py
ygt/ygYAMLEditor.py
ygt/ygridfit.py
ygt/fonts/SourceCodePro-Regular.ttf
ygt/icons/align.png
ygt/icons/anchor.png
ygt/icons/black_distance.png
ygt/icons/cursor-icon-off.png
ygt/icons/cursor-icon-on.png
ygt/icons/cv.png
ygt/icons/cv_guess.png
ygt/icons/gray_distance.png
ygt/icons/hand-icon-off.png
ygt/icons/hand-icon-on.png
ygt/icons/horizontal-off.png
ygt/icons/horizontal-on.png
ygt/icons/interpolate.png
ygt/icons/make_set.png
ygt/icons/program.png
ygt/icons/shift.png
ygt/icons/stem_distance.png
ygt/icons/vertical-off.png
ygt/icons/vertical-on.png
ygt/icons/white_distance.png
ygt-0.2.7.dist-info/LICENSE
ygt-0.2.7.dist-info/METADATA
ygt-0.2.7.dist-info/WHEEL
ygt-0.2.7.dist-info/entry_points.txt
ygt-0.2.7.dist-info/top_level.txt
ygt-0.2.7.dist-info/RECORD
