Metadata-Version: 2.2
Name: ygt
Version: 0.2.7
Summary: A graphical hint editor for TrueType fonts
Author-email: "Peter S. Baker" <b.tarde@mail.com>
Classifier: Programming Language :: Python :: 3
Classifier: License :: OSI Approved :: Apache Software License
Classifier: Operating System :: OS Independent
Requires-Python: >=3.10.4
License-File: LICENSE
Requires-Dist: PyQt6>=6.4.0
Requires-Dist: fonttools>=4.38.0
Requires-Dist: freetype-py>=2.3.0
Requires-Dist: defcon>=0.10.1
Requires-Dist: xgridfit>=3.3.0
Requires-Dist: setuptools>=65.3.0
Requires-Dist: PyYAML>=6.0
Requires-Dist: schema>=0.7.5
Requires-Dist: fs>=2.4.15
Requires-Dist: ufo2ft>=2.28.0
Requires-Dist: numpy>=1.22.4
Requires-Dist: uharfbuzz>=0.25.0
